datacatalog_tag_exporter/__init__.py
datacatalog_tag_exporter/constant.py
datacatalog_tag_exporter/datacatalog_facade.py
datacatalog_tag_exporter/datacatalog_tag_exporter_cli.py
datacatalog_tag_exporter/tag_datasource_exporter.py
datacatalog_tag_exporter-0.3.2.dist-info/AUTHORS.rst
datacatalog_tag_exporter-0.3.2.dist-info/LICENSE
datacatalog_tag_exporter-0.3.2.dist-info/METADATA
datacatalog_tag_exporter-0.3.2.dist-info/WHEEL
datacatalog_tag_exporter-0.3.2.dist-info/entry_points.txt
datacatalog_tag_exporter-0.3.2.dist-info/top_level.txt
datacatalog_tag_exporter-0.3.2.dist-info/RECORD
