Metadata-Version: 2.1
Name: datacatalog-tag-exporter
Version: 0.3.2
Summary: A package to manage Google Cloud Data Catalog  Tag export scripts
Home-page: https://github.com/mesmacosta/datacatalog-tag-exporter
Author: Marcelo Miranda
Author-email: mesmacosta@gmail.com
License: MIT license
Platform: Posix; MacOS X; Windows
Classifier: Development Status :: 3 - Alpha
Classifier: Natural Language :: English
Classifier: Programming Language :: Python
Classifier: Programming Language :: Python :: 3.6
Classifier: Programming Language :: Python :: 3.7
Requires-Python: >=3.6
Requires-Dist: google-cloud-datacatalog (<2,>=1)
Requires-Dist: pandas
Requires-Dist: tabulate
